asdk_plugin_investment_operations/__init__.py
asdk_plugin_investment_operations/api_registry.py
asdk_plugin_investment_operations/domain_apis_list.json
asdk_plugin_investment_operations/agraph/__init__.py
asdk_plugin_investment_operations/agraph/investment_operations/__init__.py
asdk_plugin_investment_operations/agraph/investment_operations/asset_lifecycle/__init__.py
asdk_plugin_investment_operations/agraph/investment_operations/asset_lifecycle/corporate_action/__init__.py
asdk_plugin_investment_operations/agraph/investment_operations/asset_lifecycle/corporate_action/v1/__init__.py
asdk_plugin_investment_operations/agraph/investment_operations/asset_lifecycle/corporate_action/v1/CorporateActionAPI/__init__.py
asdk_plugin_investment_operations/agraph/investment_operations/asset_lifecycle/corporate_action/v1/CorporateActionAPI/api_client.py
asdk_plugin_investment_operations/agraph/investment_operations/asset_lifecycle/corporate_action/v1/CorporateActionAPI/api_response.py
asdk_plugin_investment_operations/agraph/investment_operations/asset_lifecycle/corporate_action/v1/CorporateActionAPI/configuration.py
asdk_plugin_investment_operations/agraph/investment_operations/asset_lifecycle/corporate_action/v1/CorporateActionAPI/exceptions.py
asdk_plugin_investment_operations/agraph/investment_operations/asset_lifecycle/corporate_action/v1/CorporateActionAPI/rest.py
asdk_plugin_investment_operations/agraph/investment_operations/asset_lifecycle/corporate_action/v1/CorporateActionAPI/swagger.json
asdk_plugin_investment_operations/agraph/investment_operations/asset_lifecycle/corporate_action/v1/CorporateActionAPI/api/__init__.py
asdk_plugin_investment_operations/agraph/investment_operations/asset_lifecycle/corporate_action/v1/CorporateActionAPI/api/default_corporate_action_api.py
asdk_plugin_investment_operations/agraph/investment_operations/asset_lifecycle/corporate_action/v1/CorporateActionAPI/models/__init__.py
asdk_plugin_investment_operations-2.0.0b2.dist-info/METADATA
asdk_plugin_investment_operations-2.0.0b2.dist-info/WHEEL
asdk_plugin_investment_operations-2.0.0b2.dist-info/top_level.txt
asdk_plugin_investment_operations-2.0.0b2.dist-info/RECORD
